{"cameraMode":{"drawMode":0,"name":"Shaded","section":"Shading Mode"},"sceneLighting":true,"audioPlay":false,"sceneViewState":{"m_AlwaysRefresh":false,"showFog":true,"showSkybox":true,"showFlares":true,"showImageEffects":true,"showParticleSystems":true,"showVisualEffectGraphs":true,"m_FxEnabled":true},"in2DMode":false,"pivot":{"x":-4.921417236328125,"y":1.997594952583313,"z":-8.602758407592774},"rotation":{"x":-0.1930382400751114,"y":-0.6725108027458191,"z":0.18625381588935853,"w":-0.6901077628135681},"size":0.06549409031867981,"orthographic":false}